watchmen_boot/__init__.py
watchmen_boot/cache/__init__.py
watchmen_boot/cache/cache_manage.py
watchmen_boot/config/__init__.py
watchmen_boot/config/config.py
watchmen_boot/constants/__init__.py
watchmen_boot/constants/database/__init__.py
watchmen_boot/constants/database/constant.py
watchmen_boot/guid/__init__.py
watchmen_boot/guid/remoteid.py
watchmen_boot/guid/snowflake.py
watchmen_boot/guid/storage/__init__.py
watchmen_boot/guid/storage/choise_storage.py
watchmen_boot/guid/storage/mongo/__init__.py
watchmen_boot/guid/storage/mongo/mongo_template.py
watchmen_boot/guid/storage/mysql/__init__.py
watchmen_boot/guid/storage/mysql/mysql_template.py
watchmen_boot/guid/storage/oracle/__init__.py
watchmen_boot/guid/storage/oracle/oracle_template.py
watchmen_boot/logging/__init__.py
watchmen_boot/logging/log.py
watchmen_boot/model/__init__.py
watchmen_boot/model/watchmen_model.py
watchmen_boot/storage/__init__.py
watchmen_boot/storage/model/__init__.py
watchmen_boot/storage/model/data_source.py
watchmen_boot/storage/mongo/__init__.py
watchmen_boot/storage/mongo/index.py
watchmen_boot/storage/mongo/mongo_client.py
watchmen_boot/storage/mysql/__init__.py
watchmen_boot/storage/mysql/mysql_client.py
watchmen_boot/storage/mysql/mysql_utils.py
watchmen_boot/storage/oracle/__init__.py
watchmen_boot/storage/oracle/oracle_client.py
watchmen_boot/storage/oracle/oracle_utils.py
watchmen_boot/storage/utility/__init__.py
watchmen_boot/storage/utility/date_utils.py
watchmen_boot/utils/__init__.py
watchmen_boot/utils/datasource_utils.py
watchmen_boot/utils/date_func.py
watchmen_boot/utils/singleton.py
watchmen_boot-15.2.12.dist-info/LICENSE
watchmen_boot-15.2.12.dist-info/WHEEL
watchmen_boot-15.2.12.dist-info/METADATA
watchmen_boot-15.2.12.dist-info/RECORD
