Metadata-Version: 2.1
Name: watchmen-boot
Version: 15.2.12
Summary: 
Author: luke0623
Author-email: luke0623@outlook.com
Requires-Python: >=3.9,<4.0
Classifier: Programming Language :: Python :: 3
Classifier: Programming Language :: Python :: 3.10
Classifier: Programming Language :: Python :: 3.9
Requires-Dist: PyMySQL (>=1.0.2,<2.0.0)
Requires-Dist: SQLAlchemy (>=1.4.27,<2.0.0)
Requires-Dist: arrow (>=1.1.0,<2.0.0)
Requires-Dist: cacheout (>=0.13.1,<0.14.0)
Requires-Dist: cx-Oracle (>=8.2.1,<9.0.0)
Requires-Dist: pydantic (>=1.8.2,<2.0.0)
Requires-Dist: pymongo (>=3.11.4,<4.0.0)
Requires-Dist: python-dotenv (>=0.19.2,<0.20.0)
Requires-Dist: python-json-logger (>=2.0.2,<3.0.0)
Requires-Dist: requests (>=2.25.1,<3.0.0)
